crep/__init__.py
crep/base.py
crep/table.py
crep/tools.py
crep-2025.1.8.dist-info/licenses/LICENSE
data/advanced_left.csv
data/advanced_right.csv
data/base_left.csv
data/base_right.csv
doc/source/conf.py
examples/illustration.py
test/__init__.py
test/conftest.py
test/test_base.py
test/test_table.py
test/test_tools.py
crep-2025.1.8.dist-info/METADATA
crep-2025.1.8.dist-info/WHEEL
crep-2025.1.8.dist-info/top_level.txt
crep-2025.1.8.dist-info/RECORD
