Metadata-Version: 2.4
Name: crep
Version: 2025.1.8
Author-email: Vincent Laurent <vincent.laurent@mews-labs.com>
Requires-Python: >=3.6
License-File: LICENSE
Requires-Dist: pandas>1
Requires-Dist: numpy
Dynamic: license-file
